everywhere/__init__.py
everywhere/__main__.py
everywhere/api_booster.py
everywhere/attrpath.py
everywhere/attrs_utils.py
everywhere/client.py
everywhere/cmdline.py
everywhere/context.py
everywhere/gunicorn_conf.py
everywhere/kvtools.py
everywhere/myobject.py
everywhere/pydirect.py
everywhere/pyfire.py
everywhere/pyrun.py
everywhere/test.py
everywhere/test3.py
everywhere/test_util.py
everywhere/util.py
everywhere/schema_store/__init__.py
everywhere/schema_store/build_air_update.py
everywhere/schema_store/utils.py
everywhere/schema_store/airprodsearch/__init__.py
everywhere/schema_store/airprodsearch/data_types.py
everywhere/schema_store/offline/__init__.py
everywhere/schema_store/offline/build_air_update.py
everywhere_wbnupku-0.0.1.dist-info/LICENSE
everywhere_wbnupku-0.0.1.dist-info/METADATA
everywhere_wbnupku-0.0.1.dist-info/WHEEL
everywhere_wbnupku-0.0.1.dist-info/top_level.txt
everywhere_wbnupku-0.0.1.dist-info/RECORD
