Metadata-Version: 2.1
Name: everywhere-wbnupku
Version: 0.0.1
Summary: excecute python code anywhere
Home-page: https://github.com/pypa/sampleproject
Author: Wang, Xiao
Author-email: wbnupku@gmail.com
License: UNKNOWN
Platform: UNKNOWN
Classifier: Programming Language :: Python :: 3
Classifier: License :: OSI Approved :: MIT License
Classifier: Operating System :: OS Independent
